LICENSE
README.md
setup.py
balticlsc/__init__.py
balticlsc/computation_module/__init__.py
balticlsc/computation_module/api_access/__init__.py
balticlsc/computation_module/api_access/job_controller.py
balticlsc/computation_module/api_access/tokens_proxy.py
balticlsc/computation_module/baltic_lsc/__init__.py
balticlsc/computation_module/baltic_lsc/data_handle.py
balticlsc/computation_module/baltic_lsc/data_handler.py
balticlsc/computation_module/baltic_lsc/job_engine.py
balticlsc/computation_module/baltic_lsc/job_registry.py
balticlsc/computation_module/data_access/__init__.py
balticlsc/computation_module/data_access/mongo_data_handle.py
balticlsc/computation_module/data_model/__init__.py
balticlsc/computation_module/data_model/messages.py
balticlsc/computation_module/data_model/pins_configuration.py
balticlsc/computation_module/utils/__init__.py
balticlsc/computation_module/utils/logger.py
balticlsc/computation_module/utils/utils.py
balticlsc_test.egg-info/PKG-INFO
balticlsc_test.egg-info/SOURCES.txt
balticlsc_test.egg-info/dependency_links.txt
balticlsc_test.egg-info/requires.txt
balticlsc_test.egg-info/top_level.txt
examples/__init__.py
examples/empty_template/__init__.py
examples/empty_template/module/__init__.py
examples/empty_template/module/my_token_listener.py
examples/face_recogniser/__init__.py
examples/face_recogniser/script.py
examples/face_recogniser/module/__init__.py
examples/face_recogniser/module/my_token_listener.py