Metadata-Version: 2.1
Name: balticlsc-test
Version: 0.0.19
Summary: Baltic LSC module old_scheme
Home-page: https://github.com/balticlsc/Computation_Module_Template_Python
Author: BalticLSC
Author-email: Kamil.Rybinski@pw.edu.pl
License: UNKNOWN
Platform: UNKNOWN
Classifier: Programming Language :: Python :: 3
Classifier: License :: OSI Approved :: MIT License
Classifier: Operating System :: OS Independent
Requires-Python: >=3.10
